hyprnav/__init__.py
hyprnav/config.py
hyprnav/constants.py
hyprnav/listen.py
hyprnav/util.py
hyprnav/window.py
hyprnav/assets/config.yaml
hyprnav/assets/hyprnav.kdenlive
hyprnav/assets/style.css
hyprnav/assets/transition.wav
hyprnav-0.1.14.dist-info/METADATA
hyprnav-0.1.14.dist-info/WHEEL
hyprnav-0.1.14.dist-info/entry_points.txt
hyprnav-0.1.14.dist-info/licenses/LICENSE
hyprnav-0.1.14.dist-info/RECORD
