Metadata-Version: 2.4
Name: hyprnav
Version: 0.1.14
Summary: A modern and customizable workspace navigation effect for Hyprland.
Project-URL: homepage, https://github.com/antrax2024/hyprnav
Project-URL: Repository, https://github.com/antrax2024/hyprnav
Author-email: Antrax <fredcox@gmail.com>
License: MIT
License-File: LICENSE
Requires-Python: >=3.13
Requires-Dist: confz>=2.1.0
Requires-Dist: hyprpy>=0.2.0
Requires-Dist: playsound3>=3.2.3
Requires-Dist: pygobject-stubs>=2.13.0
Requires-Dist: pygobject>=3.52.3
Requires-Dist: rich>=14.0.0
